hello_tea.py
tea_xyz_kfpao93-1.0.6.dist-info/METADATA
tea_xyz_kfpao93-1.0.6.dist-info/WHEEL
tea_xyz_kfpao93-1.0.6.dist-info/entry_points.txt
tea_xyz_kfpao93-1.0.6.dist-info/top_level.txt
tea_xyz_kfpao93-1.0.6.dist-info/RECORD
